setup.cfg
setup.py
mapchete_numpy/__init__.py
mapchete_numpy.egg-info/PKG-INFO
mapchete_numpy.egg-info/SOURCES.txt
mapchete_numpy.egg-info/dependency_links.txt
mapchete_numpy.egg-info/entry_points.txt
mapchete_numpy.egg-info/requires.txt
mapchete_numpy.egg-info/top_level.txt